rustic_ai/huggingface/__init__.py
rustic_ai/huggingface/agents/__init__.py
rustic_ai/huggingface/agents/diffusion/__init__.py
rustic_ai/huggingface/agents/diffusion/pix2pix.py
rustic_ai/huggingface/agents/diffusion/stable_diffusion_agent.py
rustic_ai/huggingface/agents/llm/__init__.py
rustic_ai/huggingface/agents/llm/phi_agent.py
rustic_ai/huggingface/agents/models.py
rustic_ai/huggingface/agents/nlp/__init__.py
rustic_ai/huggingface/agents/nlp/squad_agent.py
rustic_ai/huggingface/agents/text_to_speech/__init__.py
rustic_ai/huggingface/agents/text_to_speech/speecht5_tts_agent.py
rustic_ai/huggingface/inference_mixin.py
rusticai_huggingface-1.0.0.dist-info/METADATA
rusticai_huggingface-1.0.0.dist-info/WHEEL
rusticai_huggingface-1.0.0.dist-info/RECORD
