Metadata-Version: 2.4
Name: rusticai-huggingface
Version: 1.0.0
Summary: Rustic AI module with huggingface integrations
License-Expression: Apache-2.0
Author: Dragonscale Industries Inc.
Author-email: dev@dragonscale.ai
Requires-Python: >=3.12,<3.13
Classifier: Programming Language :: Python :: 3
Classifier: Programming Language :: Python :: 3.12
Provides-Extra: test
Requires-Dist: datasets (>=3.5.0,<4.0.0)
Requires-Dist: diffusers (>=0.33.1,<0.34.0)
Requires-Dist: pillow (>=11.2.1,<12.0.0)
Requires-Dist: protobuf (>=5,<6)
Requires-Dist: rusticai-core (>=1.0.0,<1.1.0)
Requires-Dist: sentence-transformers (>=4.1.0,<5.0.0)
Requires-Dist: sentencepiece (>=0.2.0,<0.3.0)
Requires-Dist: soundfile (>=0.13.1,<0.14.0)
Requires-Dist: torch (>=2.4.0,<3.0.0) ; sys_platform == "darwin"
Requires-Dist: torch (>=2.4.0,<3.0.0) ; sys_platform == "linux"
Requires-Dist: transformers (>=4.51.2,<5.0.0)
Project-URL: Homepage, https://www.rustic.ai/
Project-URL: Repository, https://github.com/rustic-ai/rustic-ai
Project-URL: Rustic AI Core, https://pypi.org/project/rusticai-core/
